zegami_sdk/__init__.py
zegami_sdk/_annotation_methods.py
zegami_sdk/annotation.py
zegami_sdk/client.py
zegami_sdk/collection.py
zegami_sdk/helper.py
zegami_sdk/nodes.py
zegami_sdk/source.py
zegami_sdk/stats.py
zegami_sdk/test.py
zegami_sdk/util.py
zegami_sdk/workspace.py
zegami_sdk-0.4.9.dist-info/LICENSE.md
zegami_sdk-0.4.9.dist-info/METADATA
zegami_sdk-0.4.9.dist-info/WHEEL
zegami_sdk-0.4.9.dist-info/top_level.txt
zegami_sdk-0.4.9.dist-info/RECORD
