Metadata-Version: 2.1
Name: zegami-sdk
Version: 0.4.9
Summary: A suite of tools for interacting with Zegami through Python.
Home-page: https://github.com/zegami/zegami-python-sdk
Author: Zegami Ltd
Author-email: help@zegami.com
License: Apache 2.0
Platform: UNKNOWN
Requires-Python: >=3.6
License-File: LICENSE.md
Requires-Dist: azure-storage-blob (>=12.8.1)
Requires-Dist: pathlib (>=1.0)
Requires-Dist: numpy (>=1.17.0)
Requires-Dist: pandas (>=1.0.0)
Requires-Dist: Pillow (>=7.0.0)
Requires-Dist: requests (>=2.22.0)
Requires-Dist: tqdm (>=4.29.0)
Requires-Dist: urllib3 (>=1.25.2)
Requires-Dist: python-magic-bin ; platform_system == "Windows" or sys_platform == "darwin"
Requires-Dist: python-magic (>=0.4.24) ; sys_platform == "linux"
